odoo/addons/account_bank_statement_import_online_qonto/README.rst
odoo/addons/account_bank_statement_import_online_qonto/__init__.py
odoo/addons/account_bank_statement_import_online_qonto/__manifest__.py
odoo/addons/account_bank_statement_import_online_qonto/i18n/account_bank_statement_import_online_qonto.pot
odoo/addons/account_bank_statement_import_online_qonto/models/__init__.py
odoo/addons/account_bank_statement_import_online_qonto/models/online_bank_statement_provider_qonto.py
odoo/addons/account_bank_statement_import_online_qonto/static/description/icon.png
odoo/addons/account_bank_statement_import_online_qonto/tests/__init__.py
odoo/addons/account_bank_statement_import_online_qonto/tests/test_account_bank_statement_import_online_qonto.py
odoo/addons/account_bank_statement_import_online_qonto/view/online_bank_statement_provider.xml
odoo12_addon_account_bank_statement_import_online_qonto-12.0.1.0.0.99.dev1.dist-info/METADATA
odoo12_addon_account_bank_statement_import_online_qonto-12.0.1.0.0.99.dev1.dist-info/WHEEL
odoo12_addon_account_bank_statement_import_online_qonto-12.0.1.0.0.99.dev1.dist-info/top_level.txt
odoo12_addon_account_bank_statement_import_online_qonto-12.0.1.0.0.99.dev1.dist-info/RECORD
