Metadata-Version: 2.1
Name: odoo12-addon-account-bank-statement-import-online-qonto
Version: 12.0.1.0.0.99.dev1
Summary: Online Bank Statements: Qonto.eu
Home-page: https://github.com/OCA/bank-statement-import
Author: Florent de Labarre, Odoo Community Association (OCA)
Author-email: support@odoo-community.org
License: AGPL-3
Platform: UNKNOWN
Classifier: Programming Language :: Python
Classifier: Framework :: Odoo
Classifier: License :: OSI Approved :: GNU Affero General Public License v3
Requires-Python: >=3.5
Requires-Dist: odoo12-addon-account-bank-statement-import-online
Requires-Dist: odoo (<12.1dev,>=12.0a)
